esp_metrics_cli/__init__.py
esp_metrics_cli/__main__.py
esp_metrics_cli/utils.py
esp_metrics_cli/cli/__init__.py
esp_metrics_cli/cli/_options.py
esp_metrics_cli/cli/metrics_group.py
esp_metrics_cli/clients/__init__.py
esp_metrics_cli/clients/minio_client.py
esp_metrics_cli/models/__init__.py
esp_metrics_cli/models/config.py
esp_metrics_cli/models/metrics.py
esp_metrics_cli/models/result.py
esp_metrics_cli/schema/metrics_schema.json
esp_metrics_cli/templates/.esp_metrics.toml
esp_metrics_cli/templates/__init__.py
esp_metrics_cli/uploaders/__init__.py
esp_metrics_cli/uploaders/metrics_uploader.py
esp_metrics_cli/validators/__init__.py
esp_metrics_cli/validators/metrics_validator.py
esp_metrics_cli-0.5.0.dist-info/METADATA
esp_metrics_cli-0.5.0.dist-info/WHEEL
esp_metrics_cli-0.5.0.dist-info/entry_points.txt
esp_metrics_cli-0.5.0.dist-info/licenses/LICENSE
esp_metrics_cli-0.5.0.dist-info/RECORD
