Metadata-Version: 2.4
Name: esp-metrics-cli
Version: 0.5.0
Summary: ESP Metrics CLI - Command-line tool for validating and uploading project metrics
Author-email: Espressif - Aleksei Apaseev <aleksei.apaseev@espressif.com>
License: Apache-2.0
License-File: LICENSE
Classifier: Programming Language :: Python :: 3
Requires-Python: >=3.10
Requires-Dist: click>=8.0.0
Requires-Dist: jsonschema>=4.0.0
Requires-Dist: minio>=7.0.0
Requires-Dist: pydantic-settings>=2.0.0
Requires-Dist: pydantic>=2.0.0
Requires-Dist: python-dotenv>=1.0.0
Requires-Dist: pyyaml>=6.0.0
Requires-Dist: tomli>=2.0.0
Requires-Dist: tomlkit>=0.13.3
Requires-Dist: types-pyyaml>=6.0.12.20250516
Provides-Extra: ci-quality
Requires-Dist: ruff>=0.0.292; extra == 'ci-quality'
Requires-Dist: types-requests>=2.32.0.20240712; extra == 'ci-quality'
Provides-Extra: dev
Requires-Dist: czespressif>=1.2.0; extra == 'dev'
Requires-Dist: pre-commit>=4.0.1; extra == 'dev'
Requires-Dist: pyinstaller>=6.0.0; extra == 'dev'
Requires-Dist: pytest-sugar>=1.0.0; extra == 'dev'
Requires-Dist: ruff>=0.0.292; extra == 'dev'
Requires-Dist: types-requests>=2.32.0.20240712; extra == 'dev'
Provides-Extra: test
Requires-Dist: pytest-asyncio>=0.21.1; extra == 'test'
Requires-Dist: pytest-cov>=4.1.0; extra == 'test'
Requires-Dist: pytest-env>=1.1.3; extra == 'test'
Requires-Dist: pytest-xdist>=3.6.1; extra == 'test'
Requires-Dist: pytest>=7.4.0; extra == 'test'
